sysinfolib/__init__.py
sysinfolib/informers.py
sysinfolib-0.1.0.dist-info/licenses/LICENSE
sysinfolib-0.1.0.dist-info/METADATA
sysinfolib-0.1.0.dist-info/WHEEL
sysinfolib-0.1.0.dist-info/top_level.txt
sysinfolib-0.1.0.dist-info/RECORD
