Metadata-Version: 2.4
Name: sysinfolib
Version: 0.1.0
Summary: Library for obtaining system information and user information..
Home-page: https://github.com/smartlegionlab/sysinfolib/
Author: A.A. Suvorov
Author-email: smartlegiondev@gmail.com
License: BSD 3-Clause License
Project-URL: Documentation, https://github.com/smartlegionlab/sysinfolib/blob/master/README.md
Project-URL: Release notes, https://github.com/smartlegionlab/sysinfolib/releases
Keywords: sysinfolib,smartlegionlab
Classifier: Development Status :: 5 - Production/Stable
Classifier: License :: OSI Approved :: BSD License
Classifier: Natural Language :: English
Classifier: Operating System :: OS Independent
Classifier: Operating System :: POSIX :: Linux
Classifier: Programming Language :: Python :: 3 :: Only
Classifier: Topic :: Software Development :: Libraries :: Python Modules
Requires-Python: >=3.6
License-File: LICENSE
Requires-Dist: requests~=2.32.3
Requires-Dist: psutil~=5.9.8
Dynamic: license-file
